odoo/addons/account_currency_communication/LICENSE
odoo/addons/account_currency_communication/README.rst
odoo/addons/account_currency_communication/__init__.py
odoo/addons/account_currency_communication/__manifest__.py
odoo/addons/account_currency_communication/images/screen.png
odoo/addons/account_currency_communication/models/__init__.py
odoo/addons/account_currency_communication/models/account_move.py
odoo/addons/account_currency_communication/models/res_currency.py
odoo/addons/account_currency_communication/static/description/icon.png
odoo/addons/account_currency_communication/static/description/index.html
odoo/addons/account_currency_communication/tests/TEST_INSTRUCTIONS.rst
odoo/addons/account_currency_communication/views/res_currency_views.xml
odoo_addon_account_currency_communication-18.0.1.0.0.dist-info/METADATA
odoo_addon_account_currency_communication-18.0.1.0.0.dist-info/WHEEL
odoo_addon_account_currency_communication-18.0.1.0.0.dist-info/top_level.txt
odoo_addon_account_currency_communication-18.0.1.0.0.dist-info/RECORD
